[{"senator": "Jamie Raskin", "party": "Democrat", "sentence": "\u2026Hunt      Hurd (CO)      Issa      Jack      Jackson (TX)      James      Johnson (LA)      Johnson (SD)      Jordan      Joyce (OH)      Joyce (PA)      Kean      Kelly (MS)      Kelly (PA)      Kennedy (UT)      Kiggans (VA)      Kiley (CA)      Kim      Knott      Kustoff      LaHood      LaLota      LaMalfa      Langworthy      Latta      Lawler\u2026", "date": "2025-04-09", "source_url": "https://justfacts.votesmart.org/public-statement/1689975/no-rogue-rulings-act-of-2025"}, {"senator": "Robin Kelly", "party": "Democrat", "sentence": "Ms. KELLY of Illinois. Mr. Speaker, I rise today as the chair of the  Congressional Black Caucus Health Braintrust to urge my colleagues  across the aisle to extend the ACA tax credits.\u2026", "date": "2025-12-01", "source_url": "https://justfacts.votesmart.org/public-statement/1697214/medical-bills-are-too-high"}, {"senator": "Richard Neal", "party": "Democrat", "sentence": "\u2026Hinson      Houchin      Hudson      Huizenga      Issa      Jack      Jackson (TX)      James      Johnson (LA)      Johnson (SD)      Jordan      Joyce (PA)      Kelly (MS)      Kelly (PA)      Kennedy (UT)      Kiggans (VA)      Kiley (CA)      Kim      Knott      Kustoff      LaHood      Langworthy      Latta      Lee (FL)      Letlow      Loudermilk\u2026", "date": "2026-01-08", "source_url": "https://justfacts.votesmart.org/public-statement/1698788/breaking-the-gridlock-act"}, {"senator": "Jared Huffman", "party": "Democrat", "sentence": "\u2026Huizenga      Hunt      Hurd (CO)      Issa      Jack      Jackson (TX)      James      Johnson (SD)      Jordan      Joyce (OH)      Joyce (PA)      Kean      Kelly (MS)      Kelly (PA)      Kennedy (UT)      Kiggans (VA)      Kiley (CA)      Kim      Knott      Kustoff      LaLota      LaMalfa      Langworthy      Latta      Lawler      Lee (FL)\u2026", "date": "2025-05-08", "source_url": "https://justfacts.votesmart.org/public-statement/1690937/gulf-of-america-act"}, {"senator": "Robin Kelly", "party": "Democrat", "sentence": "Ms. KELLY of Illinois. Mr. Speaker, I thank Representative McClellan  and Representative Carter for inviting me to speak tonight.\n\nMr. Speaker, I rise today because there is a gun\u2026", "date": "2025-06-03", "source_url": "https://justfacts.votesmart.org/public-statement/1691753/national-gun-violence-awareness-month"}, {"senator": "Maxine Waters", "party": "Democrat", "sentence": "\u2026James      Jeffries      Johnson (LA)      Johnson (SD)      Johnson (TX)      Jordan      Joyce (OH)      Joyce (PA)      Kaptur      Kean      Keating      Kelly (MS)      Kelly (PA)      Kennedy (UT)      Kiggans (VA)      Kiley (CA)      Kim      Knott      Kustoff      LaHood      LaLota      LaMalfa      Landsman      Langworthy      Latta\u2026", "date": "2025-11-21", "source_url": "https://justfacts.votesmart.org/public-statement/1697150/denouncing-the-horrors-of-socialism"}, {"senator": "Rosa DeLauro", "party": "Democrat", "sentence": "\u2026Hunt      Hurd (CO)      Issa      Jack      Jackson (TX)      James      Johnson (LA)      Johnson (SD)      Jordan      Joyce (OH)      Joyce (PA)      Kean      Kelly (MS)      Kelly (PA)      Kennedy (UT)      Kiggans (VA)      Kiley (CA)      Kim      Knott      Kustoff      LaHood      LaLota      LaMalfa      Langworthy      Latta      Lawler\u2026", "date": "2025-11-12", "source_url": "https://justfacts.votesmart.org/public-statement/1696741/continuing-appropriations-and-extensions-act-2026"}, {"senator": "Robin Kelly", "party": "Democrat", "sentence": "Ms. KELLY of Illinois. Mr. Speaker, I rise in opposition to President  Trump's rescission package that steals $400 million from PEPFAR, a  lifesaving global health program.\n\nLet me\u2026", "date": "2025-06-12", "source_url": "https://justfacts.votesmart.org/public-statement/1692543/rescissions-act-of-2025"}, {"senator": "Jim Clyburn", "party": "Democrat", "sentence": "\u2026and, yes, quality healthcare, all those things that  make this country a great country.\n\nMr. Speaker, I am now pleased to yield to my distinguished colleague  from Illinois (Ms. Kelly).\n\nMr. CLYBURN. Mr. Speaker, I thank the gentlewoman for her comments.\n\nMcClellan), my co-anchor for this Special Order.\n\nMr. CLYBURN.  Pressley).\n\nMr. CLYBURN. Mr. Speaker,\u2026", "date": "2025-04-28", "source_url": "https://justfacts.votesmart.org/public-statement/1690244/health-disparities-in-minority-communities"}, {"senator": "Jim McGovern", "party": "Democrat", "sentence": "\u2026Hunt      Hurd (CO)      Issa      Jack      Jackson (TX)      James      Johnson (LA)      Johnson (SD)      Jordan      Joyce (OH)      Joyce (PA)      Kean      Kelly (MS)      Kelly (PA)      Kennedy (UT)      Kiggans (VA)      Kiley (CA)      Kim      Knott      Kustoff      LaHood      LaLota      LaMalfa      Langworthy      Latta      Lawler\u2026", "date": "2025-07-02", "source_url": "https://justfacts.votesmart.org/public-statement/1693225/providing-for-consideration-of-senate-amendment-to-hr-one-big-beautiful-bill-act"}, {"senator": "Robin Kelly", "party": "Democrat", "sentence": "Ms. KELLY of Illinois. Mr. Speaker, I rise today in defiance of  President Trump's threats to deploy the National Guard to Chicago.\n\nHe wasted $1 million every day to house the National\u2026", "date": null, "source_url": "https://justfacts.votesmart.org/public-statement/1694900/national-guard-deployment"}, {"senator": "Robin Kelly", "party": "Democrat", "sentence": "Ms. KELLY of Illinois. Mr. Speaker, I rise today because, just 2 days  ago, my Republican colleagues jammed through a budget plan that puts  the 0.1 percent above hardworking Americans.\u2026", "date": "2025-02-27", "source_url": "https://justfacts.votesmart.org/public-statement/1688258/american-families-will-pay-for-republican-tax-cut"}, {"senator": "Robin Kelly", "party": "Democrat", "sentence": "Ms. KELLY of Illinois. Mr. Speaker, I rise today in recognition of  Minority Health Awareness Month.\n\nMr. Speaker, I thank my colleagues, Congressman Clyburn and  Congresswoman McClellan,\u2026", "date": "2025-04-28", "source_url": "https://justfacts.votesmart.org/public-statement/1690242/health-disparities-in-minority-communities"}, {"senator": "Robin Kelly", "party": "Democrat", "sentence": "Ms. KELLY of Illinois. Mr. Speaker, I include in the Record the  following proclamation recognizing Ecumenical Patriarch Bartholomew I,  Archbishop of Constantinople-New Rome.\n\nWhereas,\u2026", "date": "2025-08-26", "source_url": "https://justfacts.votesmart.org/public-statement/1694760/recognizing-his-all-holiness-ecumenical-patriarch-bartholomew-i-archbishop-of-constantinople-new-rome"}, {"senator": "Jennifer McClellan", "party": "Democrat", "sentence": "\u2026dreamed of becoming a nurse, killed by gun violence.\n\nCecilia Thomas, a 5-month-old, shot and killed in Chicago, a 5-month  old.\n\nI now yield to the gentlewoman from Illinois (Ms. Kelly).\n\nMs. McCLELLAN. T'Yonna Major, a 9-year-old gymnast until gun violence  cut her life short.\n\nKingston Campbell, a 6-year-old killed when shooters were firing into  his\u2026", "date": "2025-06-03", "source_url": "https://justfacts.votesmart.org/public-statement/1691754/national-gun-violence-awareness-month"}, {"senator": "Bob Latta", "party": "Republican", "sentence": "\u2026Huizenga      Hurd (CO)      Issa      Jack      Jackson (TX)      James      Johnson (LA)      Johnson (SD)      Jordan      Joyce (OH)      Joyce (PA)      Kean      Kelly (MS)      Kelly (PA)      Kennedy (UT)      Kiggans (VA)      Kiley (CA)      Kim      Knott      Kustoff      LaHood      LaLota      LaMalfa      Langworthy      Latta      Lawler\u2026", "date": "2025-02-27", "source_url": "https://justfacts.votesmart.org/public-statement/1688289/providing-for-congressional-disapproval-of-the-rule-submitted-by-the-department-of-energy-relating-to-energy-conservation-program-energy-conservation-standards-for-consumer-gas-fired-instantaneous-water-heaters"}, {"senator": "Gabe Evans", "party": "Republican", "sentence": "\u2026Party, all while helping to  create jobs in my home State of Colorado and all across the Nation.\n\nFirst and foremost, I extend my gratitude to the gentlewoman from  Illinois (Ms. Kelly) for helping to introduce this bill with me. I am  proud to work with her in a bipartisan fashion to advance this bill  first through the Energy and Commerce Committee and\u2026", "date": "2025-06-23", "source_url": "https://justfacts.votesmart.org/public-statement/1692695/global-investment-in-american-jobs-act-of-2025"}, {"senator": "Brian Fitzpatrick", "party": "Republican", "sentence": "Mr. FITZPATRICK. Mr. Speaker, I rise today to recognize and celebrate  Ms. Kelly Botti, a respected leader, advocate, and CEO of Trumark  Credit Union, whose birthday on November 3rd provides a fitting  occasion to honor her outstanding service and dedication\u2026", "date": "2025-10-17", "source_url": "https://justfacts.votesmart.org/public-statement/1696273/recognizing-chief-executive-officer-of-trumark-credit-union-ms-kelly-botti"}, {"senator": "Bob Latta", "party": "Republican", "sentence": "\u2026legislation, H.R. 1618, the  Precision Agriculture Satellite Connectivity Act, that I was pleased to  introduce with the gentlewoman from Illinois' Second Congressional  District (Ms. Kelly).\n\nFor years, large parts of my district and rural areas across America  have lacked access to fast broadband connections.\n\nReliable internet access is more than just being\u2026", "date": "2025-07-14", "source_url": "https://justfacts.votesmart.org/public-statement/1693469/precision-agriculture-satellite-connectivity-act"}, {"senator": "Bryan Steil", "party": "Republican", "sentence": "\u2026Hunt      Hurd (CO)      Issa      Jack      Jackson (TX)      James      Johnson (LA)      Johnson (SD)      Jordan      Joyce (OH)      Joyce (PA)      Kean      Kelly (MS)      Kelly (PA)      Kennedy (UT)      Kiggans (VA)      Kiley (CA)      Kim      Knott      Kustoff      LaHood      LaLota      LaMalfa      Langworthy      Latta      Lawler\u2026", "date": "2025-04-10", "source_url": "https://justfacts.votesmart.org/public-statement/1690048/concurrent-resolution-on-the-budget-for-fiscal-year-2025"}]