[{"senator": "James Risch", "party": "Republican", "sentence": "(viii) Date Report Delivered to Congress: December 5, 2025.", "title": "Arms Sales Notification", "date": "2025-12-08"}, {"senator": "James Risch", "party": "Republican", "sentence": "(viii) Date Report Delivered to Congress: May 5, 2025.", "title": "Arms Sales Notification", "date": "2025-05-14"}, {"senator": "James Risch", "party": "Republican", "sentence": "(viii) Date Report Delivered to Congress: May 22, 2025.", "title": "Arms Sales Notification", "date": "2025-06-05"}, {"senator": "James Risch", "party": "Republican", "sentence": "(viii) Date Report Delivered to Congress: April 29, 2025.", "title": "Arms Sales Notification", "date": "2025-05-01"}, {"senator": "James Risch", "party": "Republican", "sentence": "(viii) Date Report Delivered to Congress: July 24, 2025.", "title": "Arms Sales Notification", "date": "2025-07-28"}, {"senator": "James Risch", "party": "Republican", "sentence": "(viii) Date Report Delivered to Congress: September 10,       2025.", "title": "Arms Sales Notification", "date": null}, {"senator": "James Risch", "party": "Republican", "sentence": "(viii) Date Report Delivered to Congress: May 12, 2025.", "title": "Arms Sales Notification", "date": "2025-05-13"}, {"senator": "James Risch", "party": "Republican", "sentence": "(viii) Date Report Delivered to Congress: December 1, 2025.", "title": "Arms Sales Notification", "date": "2025-12-02"}, {"senator": "James Risch", "party": "Republican", "sentence": "(viii) Date Report Delivered to Congress: September 25,       2025.", "title": "Arms Sales Notification", "date": null}, {"senator": "James Risch", "party": "Republican", "sentence": "(viii) Date Report Delivered to Congress: March 20, 2025.", "title": "Arms Sales Notification", "date": "2025-03-24"}, {"senator": "James Risch", "party": "Republican", "sentence": "(viii) Date Report Delivered to Congress: September 30,       2025.", "title": "Arms Sales Notification", "date": null}, {"senator": "James Risch", "party": "Republican", "sentence": "(viii) Date Report Delivered to Congress: September 16,       2025.", "title": "Arms Sales Notification", "date": null}, {"senator": "James Risch", "party": "Republican", "sentence": "(viii) Date Report Delivered to Congress: November 13,       2025.", "title": "Arms Sales Notification", "date": "2025-11-18"}, {"senator": "James Risch", "party": "Republican", "sentence": "(viii) Date Report Delivered to Congress: October 1, 2025.", "title": "Arms Sales Notification", "date": "2025-10-02"}, {"senator": "James Risch", "party": "Republican", "sentence": "(viii) Date Report Delivered to Congress: November 19,       2025.", "title": "Arms Sales Notification", "date": "2025-11-19"}]